Workbook

Sheet Assumptions
A1: ASSUMPTIONS — Candidate A Runway Model Inputs
A2: Every number used elsewhere in this workbook lives here as its own cell. No other sheet re-types a number — they all reference these cells. See 02-finance/UNIT-ECONOMICS.md and 02-finance/PRICING.md for full derivations. All Rs figures are INR.
A4: Input | B4: Value | C4: Status | D4: Source / note
A5: Day 0 (build start date) | B5: =DATE(2026,8,19) -> 46253 | C5: Final | D5: CHARTER.md / VENTURE-SELECTION.md — 2026-08-19
A6: Ticket price (Rs / report) | B6: 17500 | C6: Provisional | D6: PRICING.md recommended price = VENTURE-SELECTION.md midpoint of Rs 15,000-20,000; unvalidated against a real buyer — see RISKS.md Risk #2 test
A7: AI/LLM API cost per report (Rs) | B7: 250 | C7: Provisional | D7: UNIT-ECONOMICS.md: Anthropic Claude Sonnet 5 pricing $3/$15 per 1M tokens is Final (Anthropic pricing table); ~200K input / ~12K output token estimate per report is Provisional (not yet measured)
A8: Payment processing fee (% of ticket) | B8: 0.0354 | C8: Provisional / Blocked | D8: Razorpay international-card rate 3% + 18% GST = 3.54% (buyer is US/UK per ICP.md). CHARTER.md requires this be confirmed with the operator in Phase 2 — payment rail is not yet set up.
A9: Landing page + domain hosting (Rs/month) | B9: 250 | C9: Provisional | D9: Carrd Pro Standard $19/yr + ~$12/yr domain, converted at USD/INR 95.7, /12 months
A10: Cold-outbound tool cost (Rs/month) | B10: 4500 | C10: Provisional | D10: Instantly.ai Growth plan ~$47/mo at USD/INR 95.7; consistent with RISKS.md's Rs 3,000-5,000/150-touch estimate
A11: One-time build/tooling spend (Rs, Month 1 only) | B11: 45000 | C11: Provisional | D11: VENTURE-SELECTION.md '<Rs 50,000' estimate — no vendor quotes obtained yet
A12: Capital ceiling — lower bound (Rs) | B12: 200000 | C12: Final | D12: CHARTER.md: 'Capital at risk: Rs 2-3L total'
A13: Capital ceiling — upper bound (Rs) | B13: 300000 | C13: Final | D13: CHARTER.md: 'Capital at risk: Rs 2-3L total'
A14: Monthly revenue success/kill bar (Rs) | B14: 100000 | C14: Final | D14: CHARTER.md success bar: 'Rs 1L/month recurring'
A15: Operator other-income runway (months from 9-Sep-2026) | B15: 6 | C15: Final (floor) | D15: VENTURE-SELECTION.md Section 1, operator answer #1: 'Covered for 6+ months past 9 Sep 2026'; 6 used as the conservative floor, not the exact figure
A16: USD/INR exchange rate used | B16: 95.7 | C16: Final (spot, 18-Aug-2026) | D16: Market spot rate, ~$1 = Rs 95.7-95.7, sourced 2026-08-19 (see UNIT-ECONOMICS.md Sources). Flag: VENTURE-SELECTION.md's own Rs15-20k <-> $180-240 conversion implies an older/lower ~83 rate — stale, not corrected in that source file per charter rule 8.
A17: Absolute kill date (month-3 revenue deadline) | B17: =DATE(2026,11,19) -> 46345 | C17: Final | D17: VENTURE-SELECTION.md Section 6: 19 November 2026 (end of month 3 from Day 0)
A19: MARKET.md SCENARIO INPUTS (bottom-up, from 01-strategy/MARKET.md Section 2, Step 6 — not re-derived here)
A20: Scenario | B20: Touches / month | C20: Close rate | D20: Sales / month = touches x close rate
A21: Optimistic | B21: 250 | C21: 0.03 | D21: =B21*C21 -> 7.5
A22: Base case | B22: 200 | C22: 0.008 | D22: =B22*C22 -> 1.6
A23: Pessimistic | B23: 150 | C23: 0.002 | D23: =B23*C23 -> 0.3
A25: CHARTER-MAPPED SCENARIOS (Base/Slow/Dead labels per task instructions; formulas only, nothing retyped)
A26: Model scenario | B26: Touches / month | C26: Close rate | D26: Mapping rule
A27: Base | B27: =AVERAGE(B21,B22) -> 225 | C27: =AVERAGE(C21,C22) -> 0.019 | D27: Simple average of MARKET.md Optimistic + Base case ('optimistic-to-base blend', per task instructions) — the realistic 'if this works' case
A28: Slow | B28: =B22 -> 200 | C28: =C22 -> 0.008 | D28: Equal to MARKET.md Base case, unchanged
A29: Dead | B29: =B23 -> 150 | C29: =C23 -> 0.002 | D29: Equal to MARKET.md Pessimistic case, unchanged — this scenario triggers the kill criteria
A31: Methodology note: touches/month and close rate are held constant across all 12 months in every scenario sheet — no growth curve or learning-curve improvement is assumed, since no data exists to support one (CHARTER standing rule 2: never invent data). This is a static monthly run-rate model, not a ramp model.

Sheet Base
A1: BASE — MARKET.md optimistic-to-base blend (the realistic 'if this works' case)
A2: All cells below are formulas referencing the Assumptions sheet. Touches/close rate held constant across the 12-month horizon (see Assumptions methodology note).
A4: Month index | B4: 1 | C4: 2 | D4: 3 | E4: 4 | F4: 5 | G4: 6 | H4: 7 | I4: 8 | J4: 9 | K4: 10 | L4: 11 | M4: 12
A5: Month-end date | B5: =EDATE(Assumptions!$B$5,B4) -> 46284 | C5: =EDATE(Assumptions!$B$5,C4) -> 46314 | D5: =EDATE(Assumptions!$B$5,D4) -> 46345 | E5: =EDATE(Assumptions!$B$5,E4) -> 46375 | F5: =EDATE(Assumptions!$B$5,F4) -> 46406 | G5: =EDATE(Assumptions!$B$5,G4) -> 46437 | H5: =EDATE(Assumptions!$B$5,H4) -> 46465 | I5: =EDATE(Assumptions!$B$5,I4) -> 46496 | ... M5: =EDATE(Assumptions!$B$5,M4) -> 46618
A6: Outbound touches / month | B6: =Assumptions!$B$27 -> 225 | C6: =Assumptions!$B$27 -> 225 | D6: =Assumptions!$B$27 -> 225 | E6: =Assumptions!$B$27 -> 225 | F6: =Assumptions!$B$27 -> 225 | G6: =Assumptions!$B$27 -> 225 | H6: =Assumptions!$B$27 -> 225 | I6: =Assumptions!$B$27 -> 225 | ... M6: =Assumptions!$B$27 -> 225
A7: Close rate (contact -> paid) | B7: =Assumptions!$C$27 -> 0.019 | C7: =Assumptions!$C$27 -> 0.019 | D7: =Assumptions!$C$27 -> 0.019 | E7: =Assumptions!$C$27 -> 0.019 | F7: =Assumptions!$C$27 -> 0.019 | G7: =Assumptions!$C$27 -> 0.019 | H7: =Assumptions!$C$27 -> 0.019 | I7: =Assumptions!$C$27 -> 0.019 | ... M7: =Assumptions!$C$27 -> 0.019
A8: Expected sales (touches x close rate) | B8: =B6*B7 -> 4.275 | C8: =C6*C7 -> 4.275 | D8: =D6*D7 -> 4.275 | E8: =E6*E7 -> 4.275 | F8: =F6*F7 -> 4.275 | G8: =G6*G7 -> 4.275 | H8: =H6*H7 -> 4.275 | I8: =I6*I7 -> 4.275 | ... M8: =M6*M7 -> 4.275
A9: Revenue (Rs) | B9: =B8*Assumptions!$B$6 -> 74812.5 | C9: =C8*Assumptions!$B$6 -> 74812.5 | D9: =D8*Assumptions!$B$6 -> 74812.5 | E9: =E8*Assumptions!$B$6 -> 74812.5 | F9: =F8*Assumptions!$B$6 -> 74812.5 | G9: =G8*Assumptions!$B$6 -> 74812.5 | H9: =H8*Assumptions!$B$6 -> 74812.5 | I9: =I8*Assumptions!$B$6 -> 74812.5 | ... M9: =M8*Assumptions!$B$6 -> 74812.5
A10: AI/LLM variable cost (Rs) | B10: =B8*Assumptions!$B$7 -> 1068.75 | C10: =C8*Assumptions!$B$7 -> 1068.75 | D10: =D8*Assumptions!$B$7 -> 1068.75 | E10: =E8*Assumptions!$B$7 -> 1068.75 | F10: =F8*Assumptions!$B$7 -> 1068.75 | G10: =G8*Assumptions!$B$7 -> 1068.75 | H10: =H8*Assumptions!$B$7 -> 1068.75 | I10: =I8*Assumptions!$B$7 -> 1068.75 | ... M10: =M8*Assumptions!$B$7 -> 1068.75
A11: Payment processing cost (Rs) | B11: =B9*Assumptions!$B$8 -> 2648.3625 | C11: =C9*Assumptions!$B$8 -> 2648.3625 | D11: =D9*Assumptions!$B$8 -> 2648.3625 | E11: =E9*Assumptions!$B$8 -> 2648.3625 | F11: =F9*Assumptions!$B$8 -> 2648.3625 | G11: =G9*Assumptions!$B$8 -> 2648.3625 | H11: =H9*Assumptions!$B$8 -> 2648.3625 | I11: =I9*Assumptions!$B$8 -> 2648.3625 | ... M11: =M9*Assumptions!$B$8 -> 2648.3625
A12: Fixed monthly costs — hosting + outbound tool (Rs) | B12: =Assumptions!$B$9+Assumptions!$B$10 -> 4750 | C12: =Assumptions!$B$9+Assumptions!$B$10 -> 4750 | D12: =Assumptions!$B$9+Assumptions!$B$10 -> 4750 | E12: =Assumptions!$B$9+Assumptions!$B$10 -> 4750 | F12: =Assumptions!$B$9+Assumptions!$B$10 -> 4750 | G12: =Assumptions!$B$9+Assumptions!$B$10 -> 4750 | H12: =Assumptions!$B$9+Assumptions!$B$10 -> 4750 | I12: =Assumptions!$B$9+Assumptions!$B$10 -> 4750 | ... M12: =Assumptions!$B$9+Assumptions!$B$10 -> 4750
A13: One-time build/tooling cost (Rs, Month 1 only) | B13: =IF(B4=1,Assumptions!$B$11,0) -> 45000 | C13: =IF(C4=1,Assumptions!$B$11,0) -> 0 | D13: =IF(D4=1,Assumptions!$B$11,0) -> 0 | E13: =IF(E4=1,Assumptions!$B$11,0) -> 0 | F13: =IF(F4=1,Assumptions!$B$11,0) -> 0 | G13: =IF(G4=1,Assumptions!$B$11,0) -> 0 | H13: =IF(H4=1,Assumptions!$B$11,0) -> 0 | I13: =IF(I4=1,Assumptions!$B$11,0) -> 0 | ... M13: =IF(M4=1,Assumptions!$B$11,0) -> 0
A14: Total costs (Rs) | B14: =SUM(B10:B13) -> 53467.113 | C14: =SUM(C10:C13) -> 8467.1125 | D14: =SUM(D10:D13) -> 8467.1125 | E14: =SUM(E10:E13) -> 8467.1125 | F14: =SUM(F10:F13) -> 8467.1125 | G14: =SUM(G10:G13) -> 8467.1125 | H14: =SUM(H10:H13) -> 8467.1125 | I14: =SUM(I10:I13) -> 8467.1125 | ... M14: =SUM(M10:M13) -> 8467.1125
A15: Net cash flow (Rs) | B15: =B9-B14 -> 21345.388 | C15: =C9-C14 -> 66345.387 | D15: =D9-D14 -> 66345.387 | E15: =E9-E14 -> 66345.387 | F15: =F9-F14 -> 66345.387 | G15: =G9-G14 -> 66345.387 | H15: =H9-H14 -> 66345.387 | I15: =I9-I14 -> 66345.387 | ... M15: =M9-M14 -> 66345.387
A16: Cumulative net cash flow (Rs) | B16: =B15 -> 21345.388 | C16: =B16+C15 -> 87690.775 | D16: =C16+D15 -> 154036.16 | E16: =D16+E15 -> 220381.55 | F16: =E16+F15 -> 286726.94 | G16: =F16+G15 -> 353072.33 | H16: =G16+H15 -> 419417.71 | I16: =H16+I15 -> 485763.1 | J16: =I16+J15 -> 552108.49 | ... M16: =L16+M15 -> 751144.65
A17: Ceiling balance @ Rs 2L start (Rs) | B17: =Assumptions!$B$12+B16 -> 221345.39 | C17: =Assumptions!$B$12+C16 -> 287690.78 | D17: =Assumptions!$B$12+D16 -> 354036.16 | E17: =Assumptions!$B$12+E16 -> 420381.55 | F17: =Assumptions!$B$12+F16 -> 486726.94 | G17: =Assumptions!$B$12+G16 -> 553072.32 | H17: =Assumptions!$B$12+H16 -> 619417.71 | I17: =Assumptions!$B$12+I16 -> 685763.1 | ... M17: =Assumptions!$B$12+M16 -> 951144.65
A18: Ceiling balance @ Rs 3L start (Rs) | B18: =Assumptions!$B$13+B16 -> 321345.39 | C18: =Assumptions!$B$13+C16 -> 387690.78 | D18: =Assumptions!$B$13+D16 -> 454036.16 | E18: =Assumptions!$B$13+E16 -> 520381.55 | F18: =Assumptions!$B$13+F16 -> 586726.94 | G18: =Assumptions!$B$13+G16 -> 653072.32 | H18: =Assumptions!$B$13+H16 -> 719417.71 | I18: =Assumptions!$B$13+I16 -> 785763.1 | ... M18: =Assumptions!$B$13+M16 -> 1051144.6
A19: Revenue >= Rs 1,00,000 flag | B19: =IF(B9>=Assumptions!$B$14,1,0) -> 0 | C19: =IF(C9>=Assumptions!$B$14,1,0) -> 0 | D19: =IF(D9>=Assumptions!$B$14,1,0) -> 0 | E19: =IF(E9>=Assumptions!$B$14,1,0) -> 0 | F19: =IF(F9>=Assumptions!$B$14,1,0) -> 0 | G19: =IF(G9>=Assumptions!$B$14,1,0) -> 0 | H19: =IF(H9>=Assumptions!$B$14,1,0) -> 0 | I19: =IF(I9>=Assumptions!$B$14,1,0) -> 0 | ... M19: =IF(M9>=Assumptions!$B$14,1,0) -> 0
A20: Balance < 0 flag (Rs 2L ceiling) | B20: =IF(B17<0,1,0) -> 0 | C20: =IF(C17<0,1,0) -> 0 | D20: =IF(D17<0,1,0) -> 0 | E20: =IF(E17<0,1,0) -> 0 | F20: =IF(F17<0,1,0) -> 0 | G20: =IF(G17<0,1,0) -> 0 | H20: =IF(H17<0,1,0) -> 0 | I20: =IF(I17<0,1,0) -> 0 | ... M20: =IF(M17<0,1,0) -> 0
A21: Balance < 0 flag (Rs 3L ceiling) | B21: =IF(B18<0,1,0) -> 0 | C21: =IF(C18<0,1,0) -> 0 | D21: =IF(D18<0,1,0) -> 0 | E21: =IF(E18<0,1,0) -> 0 | F21: =IF(F18<0,1,0) -> 0 | G21: =IF(G18<0,1,0) -> 0 | H21: =IF(H18<0,1,0) -> 0 | I21: =IF(I18<0,1,0) -> 0 | ... M21: =IF(M18<0,1,0) -> 0
A23: SUMMARY — crossing points (all via INDEX/MATCH against the flag rows above)
A24: First month revenue >= Rs 1,00,000 | B24: =IFERROR(INDEX(B4:M4,MATCH(1,B19:M19,0)),"Not reached in 12 months") -> Not reached in 12 months
A25: Calendar date of that month-end | B25: =IFERROR(INDEX(B5:M5,MATCH(1,B19:M19,0)),"N/A") -> N/A
A26: First month cumulative balance < 0 (Rs 2L ceiling) | B26: =IFERROR(INDEX(B4:M4,MATCH(1,B20:M20,0)),"Stays solvent through month 12") -> Stays solvent through month 12
A27: Calendar date of that crossing (Rs 2L) | B27: =IFERROR(INDEX(B5:M5,MATCH(1,B20:M20,0)),"N/A") -> N/A
A28: First month cumulative balance < 0 (Rs 3L ceiling) | B28: =IFERROR(INDEX(B4:M4,MATCH(1,B21:M21,0)),"Stays solvent through month 12") -> Stays solvent through month 12
A29: Calendar date of that crossing (Rs 3L) | B29: =IFERROR(INDEX(B5:M5,MATCH(1,B21:M21,0)),"N/A") -> N/A

Sheet Slow
A1: SLOW — MARKET.md base case (harder-ask-adjusted cold-outbound benchmark)
A2: All cells below are formulas referencing the Assumptions sheet. Touches/close rate held constant across the 12-month horizon (see Assumptions methodology note).
A4: Month index | B4: 1 | C4: 2 | D4: 3 | E4: 4 | F4: 5 | G4: 6 | H4: 7 | I4: 8 | J4: 9 | K4: 10 | L4: 11 | M4: 12
A5: Month-end date | B5: =EDATE(Assumptions!$B$5,B4) -> 46284 | C5: =EDATE(Assumptions!$B$5,C4) -> 46314 | D5: =EDATE(Assumptions!$B$5,D4) -> 46345 | E5: =EDATE(Assumptions!$B$5,E4) -> 46375 | F5: =EDATE(Assumptions!$B$5,F4) -> 46406 | G5: =EDATE(Assumptions!$B$5,G4) -> 46437 | H5: =EDATE(Assumptions!$B$5,H4) -> 46465 | I5: =EDATE(Assumptions!$B$5,I4) -> 46496 | ... M5: =EDATE(Assumptions!$B$5,M4) -> 46618
A6: Outbound touches / month | B6: =Assumptions!$B$28 -> 200 | C6: =Assumptions!$B$28 -> 200 | D6: =Assumptions!$B$28 -> 200 | E6: =Assumptions!$B$28 -> 200 | F6: =Assumptions!$B$28 -> 200 | G6: =Assumptions!$B$28 -> 200 | H6: =Assumptions!$B$28 -> 200 | I6: =Assumptions!$B$28 -> 200 | ... M6: =Assumptions!$B$28 -> 200
A7: Close rate (contact -> paid) | B7: =Assumptions!$C$28 -> 0.008 | C7: =Assumptions!$C$28 -> 0.008 | D7: =Assumptions!$C$28 -> 0.008 | E7: =Assumptions!$C$28 -> 0.008 | F7: =Assumptions!$C$28 -> 0.008 | G7: =Assumptions!$C$28 -> 0.008 | H7: =Assumptions!$C$28 -> 0.008 | I7: =Assumptions!$C$28 -> 0.008 | ... M7: =Assumptions!$C$28 -> 0.008
A8: Expected sales (touches x close rate) | B8: =B6*B7 -> 1.6 | C8: =C6*C7 -> 1.6 | D8: =D6*D7 -> 1.6 | E8: =E6*E7 -> 1.6 | F8: =F6*F7 -> 1.6 | G8: =G6*G7 -> 1.6 | H8: =H6*H7 -> 1.6 | I8: =I6*I7 -> 1.6 | ... M8: =M6*M7 -> 1.6
A9: Revenue (Rs) | B9: =B8*Assumptions!$B$6 -> 28000 | C9: =C8*Assumptions!$B$6 -> 28000 | D9: =D8*Assumptions!$B$6 -> 28000 | E9: =E8*Assumptions!$B$6 -> 28000 | F9: =F8*Assumptions!$B$6 -> 28000 | G9: =G8*Assumptions!$B$6 -> 28000 | H9: =H8*Assumptions!$B$6 -> 28000 | I9: =I8*Assumptions!$B$6 -> 28000 | ... M9: =M8*Assumptions!$B$6 -> 28000
A10: AI/LLM variable cost (Rs) | B10: =B8*Assumptions!$B$7 -> 400 | C10: =C8*Assumptions!$B$7 -> 400 | D10: =D8*Assumptions!$B$7 -> 400 | E10: =E8*Assumptions!$B$7 -> 400 | F10: =F8*Assumptions!$B$7 -> 400 | G10: =G8*Assumptions!$B$7 -> 400 | H10: =H8*Assumptions!$B$7 -> 400 | I10: =I8*Assumptions!$B$7 -> 400 | ... M10: =M8*Assumptions!$B$7 -> 400
A11: Payment processing cost (Rs) | B11: =B9*Assumptions!$B$8 -> 991.2 | C11: =C9*Assumptions!$B$8 -> 991.2 | D11: =D9*Assumptions!$B$8 -> 991.2 | E11: =E9*Assumptions!$B$8 -> 991.2 | F11: =F9*Assumptions!$B$8 -> 991.2 | G11: =G9*Assumptions!$B$8 -> 991.2 | H11: =H9*Assumptions!$B$8 -> 991.2 | I11: =I9*Assumptions!$B$8 -> 991.2 | ... M11: =M9*Assumptions!$B$8 -> 991.2
A12: Fixed monthly costs — hosting + outbound tool (Rs) | B12: =Assumptions!$B$9+Assumptions!$B$10 -> 4750 | C12: =Assumptions!$B$9+Assumptions!$B$10 -> 4750 | D12: =Assumptions!$B$9+Assumptions!$B$10 -> 4750 | E12: =Assumptions!$B$9+Assumptions!$B$10 -> 4750 | F12: =Assumptions!$B$9+Assumptions!$B$10 -> 4750 | G12: =Assumptions!$B$9+Assumptions!$B$10 -> 4750 | H12: =Assumptions!$B$9+Assumptions!$B$10 -> 4750 | I12: =Assumptions!$B$9+Assumptions!$B$10 -> 4750 | ... M12: =Assumptions!$B$9+Assumptions!$B$10 -> 4750
A13: One-time build/tooling cost (Rs, Month 1 only) | B13: =IF(B4=1,Assumptions!$B$11,0) -> 45000 | C13: =IF(C4=1,Assumptions!$B$11,0) -> 0 | D13: =IF(D4=1,Assumptions!$B$11,0) -> 0 | E13: =IF(E4=1,Assumptions!$B$11,0) -> 0 | F13: =IF(F4=1,Assumptions!$B$11,0) -> 0 | G13: =IF(G4=1,Assumptions!$B$11,0) -> 0 | H13: =IF(H4=1,Assumptions!$B$11,0) -> 0 | I13: =IF(I4=1,Assumptions!$B$11,0) -> 0 | ... M13: =IF(M4=1,Assumptions!$B$11,0) -> 0
A14: Total costs (Rs) | B14: =SUM(B10:B13) -> 51141.2 | C14: =SUM(C10:C13) -> 6141.2 | D14: =SUM(D10:D13) -> 6141.2 | E14: =SUM(E10:E13) -> 6141.2 | F14: =SUM(F10:F13) -> 6141.2 | G14: =SUM(G10:G13) -> 6141.2 | H14: =SUM(H10:H13) -> 6141.2 | I14: =SUM(I10:I13) -> 6141.2 | ... M14: =SUM(M10:M13) -> 6141.2
A15: Net cash flow (Rs) | B15: =B9-B14 -> -23141.2 | C15: =C9-C14 -> 21858.8 | D15: =D9-D14 -> 21858.8 | E15: =E9-E14 -> 21858.8 | F15: =F9-F14 -> 21858.8 | G15: =G9-G14 -> 21858.8 | H15: =H9-H14 -> 21858.8 | I15: =I9-I14 -> 21858.8 | ... M15: =M9-M14 -> 21858.8
A16: Cumulative net cash flow (Rs) | B16: =B15 -> -23141.2 | C16: =B16+C15 -> -1282.4 | D16: =C16+D15 -> 20576.4 | E16: =D16+E15 -> 42435.2 | F16: =E16+F15 -> 64294 | G16: =F16+G15 -> 86152.8 | H16: =G16+H15 -> 108011.6 | I16: =H16+I15 -> 129870.4 | J16: =I16+J15 -> 151729.2 | ... M16: =L16+M15 -> 217305.6
A17: Ceiling balance @ Rs 2L start (Rs) | B17: =Assumptions!$B$12+B16 -> 176858.8 | C17: =Assumptions!$B$12+C16 -> 198717.6 | D17: =Assumptions!$B$12+D16 -> 220576.4 | E17: =Assumptions!$B$12+E16 -> 242435.2 | F17: =Assumptions!$B$12+F16 -> 264294 | G17: =Assumptions!$B$12+G16 -> 286152.8 | H17: =Assumptions!$B$12+H16 -> 308011.6 | I17: =Assumptions!$B$12+I16 -> 329870.4 | ... M17: =Assumptions!$B$12+M16 -> 417305.6
A18: Ceiling balance @ Rs 3L start (Rs) | B18: =Assumptions!$B$13+B16 -> 276858.8 | C18: =Assumptions!$B$13+C16 -> 298717.6 | D18: =Assumptions!$B$13+D16 -> 320576.4 | E18: =Assumptions!$B$13+E16 -> 342435.2 | F18: =Assumptions!$B$13+F16 -> 364294 | G18: =Assumptions!$B$13+G16 -> 386152.8 | H18: =Assumptions!$B$13+H16 -> 408011.6 | I18: =Assumptions!$B$13+I16 -> 429870.4 | ... M18: =Assumptions!$B$13+M16 -> 517305.6
A19: Revenue >= Rs 1,00,000 flag | B19: =IF(B9>=Assumptions!$B$14,1,0) -> 0 | C19: =IF(C9>=Assumptions!$B$14,1,0) -> 0 | D19: =IF(D9>=Assumptions!$B$14,1,0) -> 0 | E19: =IF(E9>=Assumptions!$B$14,1,0) -> 0 | F19: =IF(F9>=Assumptions!$B$14,1,0) -> 0 | G19: =IF(G9>=Assumptions!$B$14,1,0) -> 0 | H19: =IF(H9>=Assumptions!$B$14,1,0) -> 0 | I19: =IF(I9>=Assumptions!$B$14,1,0) -> 0 | ... M19: =IF(M9>=Assumptions!$B$14,1,0) -> 0
A20: Balance < 0 flag (Rs 2L ceiling) | B20: =IF(B17<0,1,0) -> 0 | C20: =IF(C17<0,1,0) -> 0 | D20: =IF(D17<0,1,0) -> 0 | E20: =IF(E17<0,1,0) -> 0 | F20: =IF(F17<0,1,0) -> 0 | G20: =IF(G17<0,1,0) -> 0 | H20: =IF(H17<0,1,0) -> 0 | I20: =IF(I17<0,1,0) -> 0 | ... M20: =IF(M17<0,1,0) -> 0
A21: Balance < 0 flag (Rs 3L ceiling) | B21: =IF(B18<0,1,0) -> 0 | C21: =IF(C18<0,1,0) -> 0 | D21: =IF(D18<0,1,0) -> 0 | E21: =IF(E18<0,1,0) -> 0 | F21: =IF(F18<0,1,0) -> 0 | G21: =IF(G18<0,1,0) -> 0 | H21: =IF(H18<0,1,0) -> 0 | I21: =IF(I18<0,1,0) -> 0 | ... M21: =IF(M18<0,1,0) -> 0
A23: SUMMARY — crossing points (all via INDEX/MATCH against the flag rows above)
A24: First month revenue >= Rs 1,00,000 | B24: =IFERROR(INDEX(B4:M4,MATCH(1,B19:M19,0)),"Not reached in 12 months") -> Not reached in 12 months
A25: Calendar date of that month-end | B25: =IFERROR(INDEX(B5:M5,MATCH(1,B19:M19,0)),"N/A") -> N/A
A26: First month cumulative balance < 0 (Rs 2L ceiling) | B26: =IFERROR(INDEX(B4:M4,MATCH(1,B20:M20,0)),"Stays solvent through month 12") -> Stays solvent through month 12
A27: Calendar date of that crossing (Rs 2L) | B27: =IFERROR(INDEX(B5:M5,MATCH(1,B20:M20,0)),"N/A") -> N/A
A28: First month cumulative balance < 0 (Rs 3L ceiling) | B28: =IFERROR(INDEX(B4:M4,MATCH(1,B21:M21,0)),"Stays solvent through month 12") -> Stays solvent through month 12
A29: Calendar date of that crossing (Rs 3L) | B29: =IFERROR(INDEX(B5:M5,MATCH(1,B21:M21,0)),"N/A") -> N/A

Sheet Dead
A1: DEAD — MARKET.md pessimistic case (triggers the kill criteria)
A2: All cells below are formulas referencing the Assumptions sheet. Touches/close rate held constant across the 12-month horizon (see Assumptions methodology note).
A4: Month index | B4: 1 | C4: 2 | D4: 3 | E4: 4 | F4: 5 | G4: 6 | H4: 7 | I4: 8 | J4: 9 | K4: 10 | L4: 11 | M4: 12
A5: Month-end date | B5: =EDATE(Assumptions!$B$5,B4) -> 46284 | C5: =EDATE(Assumptions!$B$5,C4) -> 46314 | D5: =EDATE(Assumptions!$B$5,D4) -> 46345 | E5: =EDATE(Assumptions!$B$5,E4) -> 46375 | F5: =EDATE(Assumptions!$B$5,F4) -> 46406 | G5: =EDATE(Assumptions!$B$5,G4) -> 46437 | H5: =EDATE(Assumptions!$B$5,H4) -> 46465 | I5: =EDATE(Assumptions!$B$5,I4) -> 46496 | ... M5: =EDATE(Assumptions!$B$5,M4) -> 46618
A6: Outbound touches / month | B6: =Assumptions!$B$29 -> 150 | C6: =Assumptions!$B$29 -> 150 | D6: =Assumptions!$B$29 -> 150 | E6: =Assumptions!$B$29 -> 150 | F6: =Assumptions!$B$29 -> 150 | G6: =Assumptions!$B$29 -> 150 | H6: =Assumptions!$B$29 -> 150 | I6: =Assumptions!$B$29 -> 150 | ... M6: =Assumptions!$B$29 -> 150
A7: Close rate (contact -> paid) | B7: =Assumptions!$C$29 -> 0.002 | C7: =Assumptions!$C$29 -> 0.002 | D7: =Assumptions!$C$29 -> 0.002 | E7: =Assumptions!$C$29 -> 0.002 | F7: =Assumptions!$C$29 -> 0.002 | G7: =Assumptions!$C$29 -> 0.002 | H7: =Assumptions!$C$29 -> 0.002 | I7: =Assumptions!$C$29 -> 0.002 | ... M7: =Assumptions!$C$29 -> 0.002
A8: Expected sales (touches x close rate) | B8: =B6*B7 -> 0.3 | C8: =C6*C7 -> 0.3 | D8: =D6*D7 -> 0.3 | E8: =E6*E7 -> 0.3 | F8: =F6*F7 -> 0.3 | G8: =G6*G7 -> 0.3 | H8: =H6*H7 -> 0.3 | I8: =I6*I7 -> 0.3 | ... M8: =M6*M7 -> 0.3
A9: Revenue (Rs) | B9: =B8*Assumptions!$B$6 -> 5250 | C9: =C8*Assumptions!$B$6 -> 5250 | D9: =D8*Assumptions!$B$6 -> 5250 | E9: =E8*Assumptions!$B$6 -> 5250 | F9: =F8*Assumptions!$B$6 -> 5250 | G9: =G8*Assumptions!$B$6 -> 5250 | H9: =H8*Assumptions!$B$6 -> 5250 | I9: =I8*Assumptions!$B$6 -> 5250 | ... M9: =M8*Assumptions!$B$6 -> 5250
A10: AI/LLM variable cost (Rs) | B10: =B8*Assumptions!$B$7 -> 75 | C10: =C8*Assumptions!$B$7 -> 75 | D10: =D8*Assumptions!$B$7 -> 75 | E10: =E8*Assumptions!$B$7 -> 75 | F10: =F8*Assumptions!$B$7 -> 75 | G10: =G8*Assumptions!$B$7 -> 75 | H10: =H8*Assumptions!$B$7 -> 75 | I10: =I8*Assumptions!$B$7 -> 75 | ... M10: =M8*Assumptions!$B$7 -> 75
A11: Payment processing cost (Rs) | B11: =B9*Assumptions!$B$8 -> 185.85 | C11: =C9*Assumptions!$B$8 -> 185.85 | D11: =D9*Assumptions!$B$8 -> 185.85 | E11: =E9*Assumptions!$B$8 -> 185.85 | F11: =F9*Assumptions!$B$8 -> 185.85 | G11: =G9*Assumptions!$B$8 -> 185.85 | H11: =H9*Assumptions!$B$8 -> 185.85 | I11: =I9*Assumptions!$B$8 -> 185.85 | ... M11: =M9*Assumptions!$B$8 -> 185.85
A12: Fixed monthly costs — hosting + outbound tool (Rs) | B12: =Assumptions!$B$9+Assumptions!$B$10 -> 4750 | C12: =Assumptions!$B$9+Assumptions!$B$10 -> 4750 | D12: =Assumptions!$B$9+Assumptions!$B$10 -> 4750 | E12: =Assumptions!$B$9+Assumptions!$B$10 -> 4750 | F12: =Assumptions!$B$9+Assumptions!$B$10 -> 4750 | G12: =Assumptions!$B$9+Assumptions!$B$10 -> 4750 | H12: =Assumptions!$B$9+Assumptions!$B$10 -> 4750 | I12: =Assumptions!$B$9+Assumptions!$B$10 -> 4750 | ... M12: =Assumptions!$B$9+Assumptions!$B$10 -> 4750
A13: One-time build/tooling cost (Rs, Month 1 only) | B13: =IF(B4=1,Assumptions!$B$11,0) -> 45000 | C13: =IF(C4=1,Assumptions!$B$11,0) -> 0 | D13: =IF(D4=1,Assumptions!$B$11,0) -> 0 | E13: =IF(E4=1,Assumptions!$B$11,0) -> 0 | F13: =IF(F4=1,Assumptions!$B$11,0) -> 0 | G13: =IF(G4=1,Assumptions!$B$11,0) -> 0 | H13: =IF(H4=1,Assumptions!$B$11,0) -> 0 | I13: =IF(I4=1,Assumptions!$B$11,0) -> 0 | ... M13: =IF(M4=1,Assumptions!$B$11,0) -> 0
A14: Total costs (Rs) | B14: =SUM(B10:B13) -> 50010.85 | C14: =SUM(C10:C13) -> 5010.85 | D14: =SUM(D10:D13) -> 5010.85 | E14: =SUM(E10:E13) -> 5010.85 | F14: =SUM(F10:F13) -> 5010.85 | G14: =SUM(G10:G13) -> 5010.85 | H14: =SUM(H10:H13) -> 5010.85 | I14: =SUM(I10:I13) -> 5010.85 | ... M14: =SUM(M10:M13) -> 5010.85
A15: Net cash flow (Rs) | B15: =B9-B14 -> -44760.85 | C15: =C9-C14 -> 239.15 | D15: =D9-D14 -> 239.15 | E15: =E9-E14 -> 239.15 | F15: =F9-F14 -> 239.15 | G15: =G9-G14 -> 239.15 | H15: =H9-H14 -> 239.15 | I15: =I9-I14 -> 239.15 | ... M15: =M9-M14 -> 239.15
A16: Cumulative net cash flow (Rs) | B16: =B15 -> -44760.85 | C16: =B16+C15 -> -44521.7 | D16: =C16+D15 -> -44282.55 | E16: =D16+E15 -> -44043.4 | F16: =E16+F15 -> -43804.25 | G16: =F16+G15 -> -43565.1 | H16: =G16+H15 -> -43325.95 | I16: =H16+I15 -> -43086.8 | J16: =I16+J15 -> -42847.65 | ... M16: =L16+M15 -> -42130.2
A17: Ceiling balance @ Rs 2L start (Rs) | B17: =Assumptions!$B$12+B16 -> 155239.15 | C17: =Assumptions!$B$12+C16 -> 155478.3 | D17: =Assumptions!$B$12+D16 -> 155717.45 | E17: =Assumptions!$B$12+E16 -> 155956.6 | F17: =Assumptions!$B$12+F16 -> 156195.75 | G17: =Assumptions!$B$12+G16 -> 156434.9 | H17: =Assumptions!$B$12+H16 -> 156674.05 | I17: =Assumptions!$B$12+I16 -> 156913.2 | ... M17: =Assumptions!$B$12+M16 -> 157869.8
A18: Ceiling balance @ Rs 3L start (Rs) | B18: =Assumptions!$B$13+B16 -> 255239.15 | C18: =Assumptions!$B$13+C16 -> 255478.3 | D18: =Assumptions!$B$13+D16 -> 255717.45 | E18: =Assumptions!$B$13+E16 -> 255956.6 | F18: =Assumptions!$B$13+F16 -> 256195.75 | G18: =Assumptions!$B$13+G16 -> 256434.9 | H18: =Assumptions!$B$13+H16 -> 256674.05 | I18: =Assumptions!$B$13+I16 -> 256913.2 | ... M18: =Assumptions!$B$13+M16 -> 257869.8
A19: Revenue >= Rs 1,00,000 flag | B19: =IF(B9>=Assumptions!$B$14,1,0) -> 0 | C19: =IF(C9>=Assumptions!$B$14,1,0) -> 0 | D19: =IF(D9>=Assumptions!$B$14,1,0) -> 0 | E19: =IF(E9>=Assumptions!$B$14,1,0) -> 0 | F19: =IF(F9>=Assumptions!$B$14,1,0) -> 0 | G19: =IF(G9>=Assumptions!$B$14,1,0) -> 0 | H19: =IF(H9>=Assumptions!$B$14,1,0) -> 0 | I19: =IF(I9>=Assumptions!$B$14,1,0) -> 0 | ... M19: =IF(M9>=Assumptions!$B$14,1,0) -> 0
A20: Balance < 0 flag (Rs 2L ceiling) | B20: =IF(B17<0,1,0) -> 0 | C20: =IF(C17<0,1,0) -> 0 | D20: =IF(D17<0,1,0) -> 0 | E20: =IF(E17<0,1,0) -> 0 | F20: =IF(F17<0,1,0) -> 0 | G20: =IF(G17<0,1,0) -> 0 | H20: =IF(H17<0,1,0) -> 0 | I20: =IF(I17<0,1,0) -> 0 | ... M20: =IF(M17<0,1,0) -> 0
A21: Balance < 0 flag (Rs 3L ceiling) | B21: =IF(B18<0,1,0) -> 0 | C21: =IF(C18<0,1,0) -> 0 | D21: =IF(D18<0,1,0) -> 0 | E21: =IF(E18<0,1,0) -> 0 | F21: =IF(F18<0,1,0) -> 0 | G21: =IF(G18<0,1,0) -> 0 | H21: =IF(H18<0,1,0) -> 0 | I21: =IF(I18<0,1,0) -> 0 | ... M21: =IF(M18<0,1,0) -> 0
A23: SUMMARY — crossing points (all via INDEX/MATCH against the flag rows above)
A24: First month revenue >= Rs 1,00,000 | B24: =IFERROR(INDEX(B4:M4,MATCH(1,B19:M19,0)),"Not reached in 12 months") -> Not reached in 12 months
A25: Calendar date of that month-end | B25: =IFERROR(INDEX(B5:M5,MATCH(1,B19:M19,0)),"N/A") -> N/A
A26: First month cumulative balance < 0 (Rs 2L ceiling) | B26: =IFERROR(INDEX(B4:M4,MATCH(1,B20:M20,0)),"Stays solvent through month 12") -> Stays solvent through month 12
A27: Calendar date of that crossing (Rs 2L) | B27: =IFERROR(INDEX(B5:M5,MATCH(1,B20:M20,0)),"N/A") -> N/A
A28: First month cumulative balance < 0 (Rs 3L ceiling) | B28: =IFERROR(INDEX(B4:M4,MATCH(1,B21:M21,0)),"Stays solvent through month 12") -> Stays solvent through month 12
A29: Calendar date of that crossing (Rs 3L) | B29: =IFERROR(INDEX(B5:M5,MATCH(1,B21:M21,0)),"N/A") -> N/A

Sheet Summary
A1: SUMMARY — headline crossing points across scenarios
A2: Every cell below links to a scenario sheet's own Summary block — nothing retyped. See 02-finance/KILL-CRITERIA.md for the calendared kill checkpoints derived from this model.
A4: Scenario | B4: First month revenue >= Rs1L | C4: Date | D4: First month balance<0 (Rs2L) | E4: Date | F4: First month balance<0 (Rs3L) | G4: Date
A5: Base | B5: =Base!B24 -> Not reached in 12 months | C5: =Base!B25 -> N/A | D5: =Base!B26 -> Stays solvent through month 12 | E5: =Base!B27 -> N/A | F5: =Base!B28 -> Stays solvent through month 12 | G5: =Base!B29 -> N/A
A6: Slow | B6: =Slow!B24 -> Not reached in 12 months | C6: =Slow!B25 -> N/A | D6: =Slow!B26 -> Stays solvent through month 12 | E6: =Slow!B27 -> N/A | F6: =Slow!B28 -> Stays solvent through month 12 | G6: =Slow!B29 -> N/A
A7: Dead | B7: =Dead!B24 -> Not reached in 12 months | C7: =Dead!B25 -> N/A | D7: =Dead!B26 -> Stays solvent through month 12 | E7: =Dead!B27 -> N/A | F7: =Dead!B28 -> Stays solvent through month 12 | G7: =Dead!B29 -> N/A
A9: Reading this table: 'Base' is MARKET.md's optimistic-to-base blend; 'Slow' is MARKET.md's base case; 'Dead' is MARKET.md's pessimistic case. Ceiling balances start from Rs 2L / Rs 3L respectively and add cumulative net cash flow — a negative value means the scenario has burned through that starting capital.
